[
    {
        "abstract-body-shape": "hourglass",
        "age": 30,
        "body-shape": "skinny",
        "face-shape": "rectangle",
        "gender": "cis woman",
        "height": 6.5,
        "skin-tone": "Sable",
        "name": "Deborah"
    },
    {
        "abstract-body-shape": "hourglass",
        "age": 31,
        "body-shape": "skinny",
        "face-shape": "circle",
        "gender": "cis man",
        "height": 6.5,
        "skin-tone": "Espresso Brown",
        "name": "Robert"
    },
    {
        "abstract-body-shape": "inverted-triangle",
        "age": 23,
        "body-shape": "muscular",
        "face-shape": "circle",
        "gender": "trans man",
        "height": 7.5,
        "skin-tone": "Teak",
        "name": "Josepth"
    },
    {
        "abstract-body-shape": "triangle",
        "age": 19,
        "body-shape": "fat",
        "face-shape": "rectangle",
        "gender": "cis woman",
        "height": 6,
        "skin-tone": "Buff",
        "name": "Melissa"
    },
    {
        "abstract-body-shape": "rectangle",
        "age": 25,
        "body-shape": "fat",
        "face-shape": "square",
        "gender": "cis man",
        "height": 5.5,
        "skin-tone": "Peaches and Cream",
        "name": "Christopher"
    },
    {
        "abstract-body-shape": "pear",
        "age": 25,
        "body-shape": "fat",
        "face-shape": "circle",
        "gender": "cis man",
        "height": 5.5,
        "skin-tone": "Alabaster",
        "name": "George"
    },
    {
        "abstract-body-shape": "triangle",
        "age": 29,
        "body-shape": "fat",
        "face-shape": "circle",
        "gender": "cis woman",
        "height": 6.5,
        "skin-tone": "Tan",
        "name": "Amanda"
    },
    {
        "abstract-body-shape": "apple",
        "age": 29,
        "body-shape": "skinny",
        "face-shape": "rectangle",
        "gender": "cis man",
        "height": 7,
        "skin-tone": "Pecan",
        "name": "Thomas"
    },
    {
        "abstract-body-shape": "inverted-triangle",
        "age": 37,
        "body-shape": "muscular",
        "face-shape": "ellipse",
        "gender": "trans man",
        "height": 6.5,
        "skin-tone": "Peaches and Cream",
        "name": "Kenneth"
    },
    {
        "abstract-body-shape": "diamond",
        "age": 18,
        "body-shape": "muscular",
        "face-shape": "circle",
        "gender": "cis woman",
        "height": 6.5,
        "skin-tone": "Almond",
        "name": "Mary"
    },
    {
        "abstract-body-shape": "rectangle",
        "age": 24,
        "body-shape": "fat",
        "face-shape": "ellipse",
        "gender": "trans man",
        "height": 7,
        "skin-tone": "Cacao",
        "name": "Richard"
    },
    {
        "abstract-body-shape": "inverted-triangle",
        "age": 18,
        "body-shape": "fat",
        "face-shape": "ellipse",
        "gender": "cis man",
        "height": 6.5,
        "skin-tone": "Espresso Brown",
        "name": "Brian"
    },
    {
        "abstract-body-shape": "hourglass",
        "age": 20,
        "body-shape": "fat",
        "face-shape": "circle",
        "gender": "cis woman",
        "height": 7.5,
        "skin-tone": "Cacao",
        "name": "Nancy"
    },
    {
        "abstract-body-shape": "hourglass",
        "age": 23,
        "body-shape": "fat",
        "face-shape": "rectangle",
        "gender": "cis man",
        "height": 7,
        "skin-tone": "Pecan",
        "name": "John"
    },
    {
        "abstract-body-shape": "hourglass",
        "age": 28,
        "body-shape": "skinny",
        "face-shape": "rectangle",
        "gender": "trans man",
        "height": 5.5,
        "skin-tone": "Pecan",
        "name": "Josepth"
    },
    {
        "abstract-body-shape": "diamond",
        "age": 24,
        "body-shape": "skinny",
        "face-shape": "ellipse",
        "gender": "cis woman",
        "height": 7.5,
        "skin-tone": "Bisque",
        "name": "Emily"
    },
    {
        "abstract-body-shape": "inverted-triangle",
        "age": 45,
        "body-shape": "skinny",
        "face-shape": "ellipse",
        "gender": "cis woman",
        "height": 6.5,
        "skin-tone": "Bronze",
        "name": "Sandra"
    },
    {
        "abstract-body-shape": "hourglass",
        "age": 23,
        "body-shape": "muscular",
        "face-shape": "ellipse",
        "gender": "cis woman",
        "height": 5.5,
        "skin-tone": "Bronze",
        "name": "Susan"
    },
    {
        "abstract-body-shape": "triangle",
        "age": 53,
        "body-shape": "skinny",
        "face-shape": "inverted-triangle",
        "gender": "cis woman",
        "height": 7,
        "skin-tone": "Almond",
        "name": "Amanda"
    },
    {
        "abstract-body-shape": "rectangle",
        "age": 19,
        "body-shape": "muscular",
        "face-shape": "circle",
        "gender": "cis man",
        "height": 7,
        "skin-tone": "Pecan",
        "name": "Richard"
    },
    {
        "abstract-body-shape": "rectangle",
        "age": 24,
        "body-shape": "muscular",
        "face-shape": "circle",
        "gender": "cis man",
        "height": 6.5,
        "skin-tone": "Almond",
        "name": "Joshua"
    },
    {
        "abstract-body-shape": "hourglass",
        "age": 23,
        "body-shape": "fat",
        "face-shape": "inverted-triangle",
        "gender": "trans man",
        "height": 6,
        "skin-tone": "Cacao",
        "name": "William"
    },
    {
        "abstract-body-shape": "diamond",
        "age": 31,
        "body-shape": "muscular",
        "face-shape": "circle",
        "gender": "cis man",
        "height": 7.5,
        "skin-tone": "Alabaster",
        "name": "Brian"
    },
    {
        "abstract-body-shape": "apple",
        "age": 28,
        "body-shape": "muscular",
        "face-shape": "square",
        "gender": "cis woman",
        "height": 7,
        "skin-tone": "Bronze",
        "name": "Susan"
    },
    {
        "abstract-body-shape": "apple",
        "age": 25,
        "body-shape": "skinny",
        "face-shape": "rectangle",
        "gender": "cis man",
        "height": 7,
        "skin-tone": "Hickory",
        "name": "Josepth"
    },
    {
        "abstract-body-shape": "inverted-triangle",
        "age": 25,
        "body-shape": "skinny",
        "face-shape": "square",
        "gender": "cis man",
        "height": 6.5,
        "skin-tone": "Praline",
        "name": "Andrew"
    },
    {
        "abstract-body-shape": "inverted-triangle",
        "age": 28,
        "body-shape": "fat",
        "face-shape": "ellipse",
        "gender": "cis man",
        "height": 7,
        "skin-tone": "Saddle Brown",
        "name": "Josepth"
    },
    {
        "abstract-body-shape": "hourglass",
        "age": 46,
        "body-shape": "muscular",
        "face-shape": "rectangle",
        "gender": "trans man",
        "height": 6.5,
        "skin-tone": "Bisque",
        "name": "Charles"
    },
    {
        "abstract-body-shape": "rectangle",
        "age": 28,
        "body-shape": "skinny",
        "face-shape": "rectangle",
        "gender": "trans man",
        "height": 7.5,
        "skin-tone": "Pecan",
        "name": "Josepth"
    },
    {
        "abstract-body-shape": "inverted-triangle",
        "age": 20,
        "body-shape": "fat",
        "face-shape": "ellipse",
        "gender": "cis woman",
        "height": 6.5,
        "skin-tone": "Praline",
        "name": "Elizabeth"
    },
    {
        "abstract-body-shape": "rectangle",
        "age": 25,
        "body-shape": "muscular",
        "face-shape": "ellipse",
        "gender": "cis man",
        "height": 6.5,
        "skin-tone": "Pecan",
        "name": "David"
    },
    {
        "abstract-body-shape": "rectangle",
        "age": 57,
        "body-shape": "fat",
        "face-shape": "inverted-triangle",
        "gender": "cis woman",
        "height": 6.5,
        "skin-tone": "Cacao",
        "name": "Barbara"
    },
    {
        "abstract-body-shape": "hourglass",
        "age": 67,
        "body-shape": "muscular",
        "face-shape": "square",
        "gender": "cis woman",
        "height": 5.5,
        "skin-tone": "Saddle Brown",
        "name": "Patricia"
    },
    {
        "abstract-body-shape": "inverted-triangle",
        "age": 24,
        "body-shape": "fat",
        "face-shape": "circle",
        "gender": "cis man",
        "height": 6.5,
        "skin-tone": "Beige",
        "name": "Richard"
    },
    {
        "abstract-body-shape": "apple",
        "age": 31,
        "body-shape": "skinny",
        "face-shape": "ellipse",
        "gender": "cis man",
        "height": 6.5,
        "skin-tone": "Ivory",
        "name": "Kenneth"
    },
    {
        "abstract-body-shape": "inverted-triangle",
        "age": 32,
        "body-shape": "skinny",
        "face-shape": "ellipse",
        "gender": "cis woman",
        "height": 6.5,
        "skin-tone": "Hickory",
        "name": "Linda"
    },
    {
        "abstract-body-shape": "hourglass",
        "age": 27,
        "body-shape": "muscular",
        "face-shape": "circle",
        "gender": "cis man",
        "height": 6.5,
        "skin-tone": "Beige",
        "name": "Josepth"
    },
    {
        "abstract-body-shape": "rectangle",
        "age": 21,
        "body-shape": "fat",
        "face-shape": "ellipse",
        "gender": "cis man",
        "height": 6.5,
        "skin-tone": "Almond",
        "name": "Michael"
    },
    {
        "abstract-body-shape": "rectangle",
        "age": 57,
        "body-shape": "fat",
        "face-shape": "inverted-triangle",
        "gender": "cis man",
        "height": 5.5,
        "skin-tone": "Porcelain",
        "name": "Andrew"
    },
    {
        "abstract-body-shape": "rectangle",
        "age": 22,
        "body-shape": "fat",
        "face-shape": "circle",
        "gender": "cis man",
        "height": 7.5,
        "skin-tone": "Espresso Brown",
        "name": "Robert"
    },
    {
        "abstract-body-shape": "rectangle",
        "age": 27,
        "body-shape": "muscular",
        "face-shape": "square",
        "gender": "cis woman",
        "height": 6.5,
        "skin-tone": "Bisque",
        "name": "Patricia"
    },
    {
        "abstract-body-shape": "inverted-triangle",
        "age": 28,
        "body-shape": "fat",
        "face-shape": "rectangle",
        "gender": "cis man",
        "height": 6.5,
        "skin-tone": "Pecan",
        "name": "Daniel"
    },
    {
        "abstract-body-shape": "rectangle",
        "age": 23,
        "body-shape": "muscular",
        "face-shape": "rectangle",
        "gender": "cis man",
        "height": 6.5,
        "skin-tone": "Carotenoid",
        "name": "Andrew"
    },
    {
        "abstract-body-shape": "square",
        "age": 68,
        "body-shape": "muscular",
        "face-shape": "square",
        "gender": "cis woman",
        "height": 7.5,
        "skin-tone": "Ivory",
        "name": "Lisa"
    },
    {
        "abstract-body-shape": "rectangle",
        "age": 22,
        "body-shape": "fat",
        "face-shape": "rectangle",
        "gender": "cis woman",
        "height": 6.5,
        "skin-tone": "Almond",
        "name": "Michelle"
    },
    {
        "abstract-body-shape": "rectangle",
        "age": 35,
        "body-shape": "skinny",
        "face-shape": "rectangle",
        "gender": "cis man",
        "height": 7.5,
        "skin-tone": "Teak",
        "name": "William"
    },
    {
        "abstract-body-shape": "rectangle",
        "age": 45,
        "body-shape": "muscular",
        "face-shape": "ellipse",
        "gender": "cis man",
        "height": 6.5,
        "skin-tone": "Buff",
        "name": "James"
    },
    {
        "abstract-body-shape": "hourglass",
        "age": 35,
        "body-shape": "muscular",
        "face-shape": "circle",
        "gender": "cis man",
        "height": 7,
        "skin-tone": "Pecan",
        "name": "Kenneth"
    },
    {
        "abstract-body-shape": "pear",
        "age": 21,
        "body-shape": "muscular",
        "face-shape": "circle",
        "gender": "trans man",
        "height": 6.5,
        "skin-tone": "Honey",
        "name": "William"
    },
    {
        "abstract-body-shape": "triangle",
        "age": 57,
        "body-shape": "fat",
        "face-shape": "ellipse",
        "gender": "trans man",
        "height": 6,
        "skin-tone": "Almond",
        "name": "Steven"
    },
    {
        "abstract-body-shape": "rectangle",
        "age": 26,
        "body-shape": "fat",
        "face-shape": "rectangle",
        "gender": "cis man",
        "height": 6.5,
        "skin-tone": "Carotenoid",
        "name": "Edward"
    },
    {
        "abstract-body-shape": "diamond",
        "age": 21,
        "body-shape": "fat",
        "face-shape": "square",
        "gender": "cis woman",
        "height": 7,
        "skin-tone": "Alabaster",
        "name": "Barbara"
    },
    {
        "abstract-body-shape": "rectangle",
        "age": 64,
        "body-shape": "fat",
        "face-shape": "circle",
        "gender": "cis woman",
        "height": 6,
        "skin-tone": "Saddle Brown",
        "name": "Jessica"
    },
    {
        "abstract-body-shape": "triangle",
        "age": 25,
        "body-shape": "fat",
        "face-shape": "circle",
        "gender": "cis man",
        "height": 6.5,
        "skin-tone": "Hickory",
        "name": "Paul"
    },
    {
        "abstract-body-shape": "hourglass",
        "age": 24,
        "body-shape": "skinny",
        "face-shape": "circle",
        "gender": "cis woman",
        "height": 6,
        "skin-tone": "Espresso Brown",
        "name": "Deborah"
    },
    {
        "abstract-body-shape": "rectangle",
        "age": 29,
        "body-shape": "skinny",
        "face-shape": "ellipse",
        "gender": "cis woman",
        "height": 6.5,
        "skin-tone": "Chestnut",
        "name": "Carol"
    },
    {
        "abstract-body-shape": "inverted-triangle",
        "age": 67,
        "body-shape": "fat",
        "face-shape": "circle",
        "gender": "cis woman",
        "height": 6,
        "skin-tone": "Praline",
        "name": "Betty"
    },
    {
        "abstract-body-shape": "hourglass",
        "age": 32,
        "body-shape": "muscular",
        "face-shape": "square",
        "gender": "cis man",
        "height": 6.5,
        "skin-tone": "Sable",
        "name": "Mark"
    },
    {
        "abstract-body-shape": "rectangle",
        "age": 52,
        "body-shape": "fat",
        "face-shape": "inverted-triangle",
        "gender": "cis man",
        "height": 5.5,
        "skin-tone": "Peaches and Cream",
        "name": "Andrew"
    },
    {
        "abstract-body-shape": "pear",
        "age": 30,
        "body-shape": "skinny",
        "face-shape": "inverted-triangle",
        "gender": "cis woman",
        "height": 5.5,
        "skin-tone": "Mahogany",
        "name": "Ashley"
    },
    {
        "abstract-body-shape": "inverted-triangle",
        "age": 28,
        "body-shape": "skinny",
        "face-shape": "ellipse",
        "gender": "trans man",
        "height": 7,
        "skin-tone": "Honey",
        "name": "William"
    },
    {
        "abstract-body-shape": "apple",
        "age": 28,
        "body-shape": "fat",
        "face-shape": "rectangle",
        "gender": "cis man",
        "height": 7,
        "skin-tone": "Caramel",
        "name": "Christopher"
    },
    {
        "abstract-body-shape": "square",
        "age": 24,
        "body-shape": "muscular",
        "face-shape": "rectangle",
        "gender": "cis woman",
        "height": 7,
        "skin-tone": "Bronze",
        "name": "Elizabeth"
    },
    {
        "abstract-body-shape": "rectangle",
        "age": 32,
        "body-shape": "fat",
        "face-shape": "ellipse",
        "gender": "trans man",
        "height": 5.5,
        "skin-tone": "Tan",
        "name": "Mark"
    },
    {
        "abstract-body-shape": "inverted-triangle",
        "age": 28,
        "body-shape": "skinny",
        "face-shape": "rectangle",
        "gender": "cis woman",
        "height": 7,
        "skin-tone": "Peaches and Cream",
        "name": "Deborah"
    },
    {
        "abstract-body-shape": "hourglass",
        "age": 22,
        "body-shape": "fat",
        "face-shape": "rectangle",
        "gender": "cis man",
        "height": 6.5,
        "skin-tone": "Hickory",
        "name": "George"
    },
    {
        "abstract-body-shape": "rectangle",
        "age": 66,
        "body-shape": "fat",
        "face-shape": "rectangle",
        "gender": "cis man",
        "height": 6,
        "skin-tone": "Bisque",
        "name": "Joshua"
    },
    {
        "abstract-body-shape": "rectangle",
        "age": 55,
        "body-shape": "fat",
        "face-shape": "ellipse",
        "gender": "trans man",
        "height": 7.5,
        "skin-tone": "Ivory",
        "name": "Kevin"
    },
    {
        "abstract-body-shape": "rectangle",
        "age": 23,
        "body-shape": "skinny",
        "face-shape": "rectangle",
        "gender": "cis woman",
        "height": 7.5,
        "skin-tone": "Almond",
        "name": "Patricia"
    },
    {
        "abstract-body-shape": "diamond",
        "age": 61,
        "body-shape": "skinny",
        "face-shape": "square",
        "gender": "cis woman",
        "height": 7,
        "skin-tone": "Hickory",
        "name": "Emily"
    },
    {
        "abstract-body-shape": "rectangle",
        "age": 33,
        "body-shape": "fat",
        "face-shape": "square",
        "gender": "cis woman",
        "height": 6.5,
        "skin-tone": "Caramel",
        "name": "Karen"
    },
    {
        "abstract-body-shape": "diamond",
        "age": 27,
        "body-shape": "skinny",
        "face-shape": "circle",
        "gender": "cis woman",
        "height": 7.5,
        "skin-tone": "Mustard",
        "name": "Linda"
    },
    {
        "abstract-body-shape": "square",
        "age": 25,
        "body-shape": "muscular",
        "face-shape": "rectangle",
        "gender": "trans man",
        "height": 7,
        "skin-tone": "Peaches and Cream",
        "name": "Joshua"
    },
    {
        "abstract-body-shape": "apple",
        "age": 23,
        "body-shape": "fat",
        "face-shape": "inverted-triangle",
        "gender": "trans man",
        "height": 5.5,
        "skin-tone": "Cacao",
        "name": "Anthony"
    },
    {
        "abstract-body-shape": "inverted-triangle",
        "age": 27,
        "body-shape": "fat",
        "face-shape": "circle",
        "gender": "cis woman",
        "height": 7,
        "skin-tone": "Chestnut",
        "name": "Lisa"
    },
    {
        "abstract-body-shape": "pear",
        "age": 35,
        "body-shape": "muscular",
        "face-shape": "circle",
        "gender": "cis man",
        "height": 7.5,
        "skin-tone": "Chestnut",
        "name": "Donald"
    },
    {
        "abstract-body-shape": "hourglass",
        "age": 22,
        "body-shape": "fat",
        "face-shape": "square",
        "gender": "cis man",
        "height": 7.5,
        "skin-tone": "Mustard",
        "name": "Thomas"
    },
    {
        "abstract-body-shape": "diamond",
        "age": 25,
        "body-shape": "fat",
        "face-shape": "circle",
        "gender": "cis woman",
        "height": 7,
        "skin-tone": "Carotenoid",
        "name": "Emily"
    },
    {
        "abstract-body-shape": "square",
        "age": 25,
        "body-shape": "muscular",
        "face-shape": "rectangle",
        "gender": "cis woman",
        "height": 6.5,
        "skin-tone": "Sable",
        "name": "Karen"
    },
    {
        "abstract-body-shape": "hourglass",
        "age": 18,
        "body-shape": "muscular",
        "face-shape": "square",
        "gender": "trans man",
        "height": 5.5,
        "skin-tone": "Honey",
        "name": "Steven"
    },
    {
        "abstract-body-shape": "rectangle",
        "age": 60,
        "body-shape": "skinny",
        "face-shape": "square",
        "gender": "cis woman",
        "height": 6.5,
        "skin-tone": "Teak",
        "name": "Linda"
    },
    {
        "abstract-body-shape": "rectangle",
        "age": 34,
        "body-shape": "muscular",
        "face-shape": "rectangle",
        "gender": "cis woman",
        "height": 7,
        "skin-tone": "Hickory",
        "name": "Deborah"
    },
    {
        "abstract-body-shape": "rectangle",
        "age": 32,
        "body-shape": "fat",
        "face-shape": "ellipse",
        "gender": "cis woman",
        "height": 5.5,
        "skin-tone": "Porcelain",
        "name": "Michelle"
    },
    {
        "abstract-body-shape": "apple",
        "age": 19,
        "body-shape": "muscular",
        "face-shape": "rectangle",
        "gender": "trans man",
        "height": 6.5,
        "skin-tone": "Honey",
        "name": "Mark"
    },
    {
        "abstract-body-shape": "inverted-triangle",
        "age": 25,
        "body-shape": "muscular",
        "face-shape": "circle",
        "gender": "cis man",
        "height": 6.5,
        "skin-tone": "Ivory",
        "name": "Joshua"
    },
    {
        "abstract-body-shape": "pear",
        "age": 27,
        "body-shape": "muscular",
        "face-shape": "rectangle",
        "gender": "cis man",
        "height": 6.5,
        "skin-tone": "Tan",
        "name": "Andrew"
    },
    {
        "abstract-body-shape": "hourglass",
        "age": 20,
        "body-shape": "fat",
        "face-shape": "rectangle",
        "gender": "cis man",
        "height": 6.5,
        "skin-tone": "Saddle Brown",
        "name": "Andrew"
    },
    {
        "abstract-body-shape": "inverted-triangle",
        "age": 65,
        "body-shape": "fat",
        "face-shape": "inverted-triangle",
        "gender": "cis man",
        "height": 6,
        "skin-tone": "Bisque",
        "name": "Robert"
    },
    {
        "abstract-body-shape": "rectangle",
        "age": 24,
        "body-shape": "skinny",
        "face-shape": "square",
        "gender": "cis man",
        "height": 7.5,
        "skin-tone": "Teak",
        "name": "Thomas"
    },
    {
        "abstract-body-shape": "hourglass",
        "age": 39,
        "body-shape": "muscular",
        "face-shape": "square",
        "gender": "cis man",
        "height": 6.5,
        "skin-tone": "Saddle Brown",
        "name": "James"
    },
    {
        "abstract-body-shape": "hourglass",
        "age": 34,
        "body-shape": "fat",
        "face-shape": "square",
        "gender": "trans man",
        "height": 6.5,
        "skin-tone": "Cacao",
        "name": "John"
    },
    {
        "abstract-body-shape": "inverted-triangle",
        "age": 33,
        "body-shape": "skinny",
        "face-shape": "circle",
        "gender": "cis woman",
        "height": 6.5,
        "skin-tone": "Saddle Brown",
        "name": "Susan"
    },
    {
        "abstract-body-shape": "apple",
        "age": 22,
        "body-shape": "fat",
        "face-shape": "circle",
        "gender": "cis man",
        "height": 5.5,
        "skin-tone": "Alabaster",
        "name": "Charles"
    },
    {
        "abstract-body-shape": "rectangle",
        "age": 31,
        "body-shape": "muscular",
        "face-shape": "inverted-triangle",
        "gender": "cis woman",
        "height": 6.5,
        "skin-tone": "Beige",
        "name": "Betty"
    },
    {
        "abstract-body-shape": "hourglass",
        "age": 45,
        "body-shape": "skinny",
        "face-shape": "circle",
        "gender": "cis man",
        "height": 5.5,
        "skin-tone": "Ivory",
        "name": "Thomas"
    },
    {
        "abstract-body-shape": "triangle",
        "age": 26,
        "body-shape": "fat",
        "face-shape": "rectangle",
        "gender": "cis man",
        "height": 6.5,
        "skin-tone": "Carotenoid",
        "name": "Andrew"
    },
    {
        "abstract-body-shape": "hourglass",
        "age": 23,
        "body-shape": "fat",
        "face-shape": "inverted-triangle",
        "gender": "trans man",
        "height": 6.5,
        "skin-tone": "Caramel",
        "name": "Mark"
    },
    {
        "abstract-body-shape": "apple",
        "age": 67,
        "body-shape": "skinny",
        "face-shape": "inverted-triangle",
        "gender": "cis woman",
        "height": 5.5,
        "skin-tone": "Alabaster",
        "name": "Jessica"
    },
    {
        "abstract-body-shape": "hourglass",
        "age": 40,
        "body-shape": "fat",
        "face-shape": "circle",
        "gender": "cis woman",
        "height": 7,
        "skin-tone": "Alabaster",
        "name": "Kimberly"
    },
    {
        "abstract-body-shape": "hourglass",
        "age": 32,
        "body-shape": "fat",
        "face-shape": "inverted-triangle",
        "gender": "trans man",
        "height": 6.5,
        "skin-tone": "Hickory",
        "name": "John"
    }
]